odoo/addons/account_payment_order_operating_unit/__init__.py
odoo/addons/account_payment_order_operating_unit/__manifest__.py
odoo/addons/account_payment_order_operating_unit/models/__init__.py
odoo/addons/account_payment_order_operating_unit/models/account_payment.py
odoo/addons/account_payment_order_operating_unit/models/account_payment_line.py
odoo/addons/account_payment_order_operating_unit/models/account_payment_order.py
odoo/addons/account_payment_order_operating_unit/models/bank_payment_line.py
odoo/addons/account_payment_order_operating_unit/security/ir.model.access.csv
odoo/addons/account_payment_order_operating_unit/views/account_payment_line.xml
odoo14_addon_account_payment_order_operating_unit-14.0.2.0.0.dist-info/METADATA
odoo14_addon_account_payment_order_operating_unit-14.0.2.0.0.dist-info/WHEEL
odoo14_addon_account_payment_order_operating_unit-14.0.2.0.0.dist-info/top_level.txt
odoo14_addon_account_payment_order_operating_unit-14.0.2.0.0.dist-info/RECORD
