Metadata-Version: 2.1
Name: odoo14-addon-account-payment-order-operating-unit
Version: 14.0.2.0.0
Summary: Configuration to properly relate payment orders and operating units
Home-page: https://git.coopdevs.org/coopdevs/odoo/odoo-addons/enhancements-operating-unit
Author: Coopdevs Treball SCCL
License: UNKNOWN
Platform: UNKNOWN
Classifier: Programming Language :: Python
Classifier: Framework :: Odoo
Classifier: Framework :: Odoo :: 14.0
Requires-Python: >=3.6
Requires-Dist: odoo14-addon-account-banking-sepa-direct-debit
Requires-Dist: odoo14-addon-account-operating-unit
Requires-Dist: odoo14-addon-account-payment-order
Requires-Dist: odoo14-addon-operating-unit
Requires-Dist: odoo (<14.1dev,>=14.0a)
